setup.cfg
setup.py
pypge/__init__.py
pypge/algebra.py
pypge/base.py
pypge/creator.py
pypge/evaluate.py
pypge/expand.py
pypge/filters.py
pypge/fitness_funcs.py
pypge/memoize.py
pypge/model.py
pypge/parallel.py
pypge/search.py
pypge/selection.py
pypge/timer.py
pypge.egg-info/PKG-INFO
pypge.egg-info/SOURCES.txt
pypge.egg-info/dependency_links.txt
pypge.egg-info/requires.txt
pypge.egg-info/top_level.txt
pypge/benchmarks/__init__.py
pypge/benchmarks/chaotic_pendulum.py
pypge/benchmarks/diffeq.py
pypge/benchmarks/diffeq_tmp.py
pypge/benchmarks/explicit.py
pypge/benchmarks/yeast.py
test/test_lmfit.py
test/test_odeint.py
test/test_sample.py