Metadata-Version: 1.0
Name: pypge
Version: 0.9
Summary: Prioritized Grammar Enumeration implementation
Home-page: https://github.com/verdverm/pypge
Author: Tony Worm
Author-email: verdverm@gmial.com
License: UNKNOWN
Keywords: pge,prioritized,grammar,enumeration,symbolic,regression,genetic programming
Platform: UNKNOWN
